LICENSE
MANIFEST.in
README.md
setup.cfg
setup.py
blobstash.egg-info/PKG-INFO
blobstash.egg-info/SOURCES.txt
blobstash.egg-info/dependency_links.txt
blobstash.egg-info/not-zip-safe
blobstash.egg-info/requires.txt
blobstash.egg-info/top_level.txt
blobstash/base/__init__.py
blobstash/base/blobstore.py
blobstash/base/client.py
blobstash/base/error.py
blobstash/base/iterator.py
blobstash/base/kvstore.py
blobstash/base/test_utils.py
blobstash/docstore/__init__.py
blobstash/docstore/attachment.py
blobstash/docstore/error.py
blobstash/docstore/query.py
blobstash/filetree/__init__.py